pi_promptflow_tools/__init__.py
pi_promptflow_tools/tools/__init__.py
pi_promptflow_tools/tools/copilot_metaprompt_tool.py
pi_promptflow_tools/tools/utils.py
pi_promptflow_tools/yamls/copilot_metaprompt_tool.yaml
tests/__init__.py
tests/test_copilot_metaprompt_tool.py
pi_promptflow_tools-3.0.1.dist-info/METADATA
pi_promptflow_tools-3.0.1.dist-info/WHEEL
pi_promptflow_tools-3.0.1.dist-info/entry_points.txt
pi_promptflow_tools-3.0.1.dist-info/top_level.txt
pi_promptflow_tools-3.0.1.dist-info/RECORD
