Metadata-Version: 2.1
Name: pi-promptflow-tools
Version: 3.0.1
Summary: A tool package for the ProcessInsights team to us for custom prompt flow tools.
